trackdo/__init__.py
trackdo/__main__.py
trackdo/cli.py
trackdo/mcp_cli.py
trackdo/py.typed
trackdo/_internal/__init__.py
trackdo/_internal/cli.py
trackdo/_internal/debug.py
trackdo/console/__init__.py
trackdo/console/_common_tasks.py
trackdo/console/aliases.py
trackdo/console/command_registry.py
trackdo/console/todo_class.py
trackdo/core/__init__.py
trackdo/core/_mcp_server.py
trackdo/core/_schemas.py
trackdo/core/_tools.py
trackdo/core/_trees.py
trackdo/core/markdown_export.py
trackdo/core/task_handler.py
trackdo/core/todo_server.py
trackdo-0.1.4.dist-info/METADATA
trackdo-0.1.4.dist-info/WHEEL
trackdo-0.1.4.dist-info/entry_points.txt
trackdo-0.1.4.dist-info/licenses/LICENSE
trackdo-0.1.4.dist-info/RECORD
