Metadata-Version: 2.4
Name: trackdo
Version: 0.1.4
Summary: TrackDo is a Todo Manager made in Python with lower level primitives made to be used through other interfaces.
Author-email: chaz <git@tachyon.top>
License-Expression: ISC
License-File: LICENSE
Requires-Python: >=3.13
Requires-Dist: bear-epoch-time>=1.1.1
Requires-Dist: bear-utils>=0.8.0
Requires-Dist: mcp[cli]>=1.10.1
Requires-Dist: prompt-toolkit>=3.0.51
Requires-Dist: pydantic>=2.11.7
Requires-Dist: python-dotenv>=1.1.1
Requires-Dist: rich>=14.0.0
Requires-Dist: sqlalchemy>=2.0.41
Requires-Dist: typer>=0.16.0
